octopus_sensing_sara/config.py
octopus_sensing_sara/interaction_module/__init__.py
octopus_sensing_sara/interaction_module/api/__init__.py
octopus_sensing_sara/interaction_module/api/dependencies.py
octopus_sensing_sara/interaction_module/api/routes.py
octopus_sensing_sara/interaction_module/chat_cli.py
octopus_sensing_sara/interaction_module/core/__init__.py
octopus_sensing_sara/interaction_module/core/config.py
octopus_sensing_sara/interaction_module/core/llm_factory.py
octopus_sensing_sara/interaction_module/core/prompt_builder.py
octopus_sensing_sara/interaction_module/main.py
octopus_sensing_sara/interaction_module/models/__init__.py
octopus_sensing_sara/interaction_module/models/database.py
octopus_sensing_sara/interaction_module/models/schemas.py
octopus_sensing_sara/interaction_module/prompts/__init__.py
octopus_sensing_sara/interaction_module/prompts/extraction_prompt/__init__.py
octopus_sensing_sara/interaction_module/prompts/extraction_prompt/handler.py
octopus_sensing_sara/interaction_module/prompts/extraction_prompt/prompt.py
octopus_sensing_sara/interaction_module/prompts/summarization_prompt/__init__.py
octopus_sensing_sara/interaction_module/prompts/summarization_prompt/handler.py
octopus_sensing_sara/interaction_module/prompts/summarization_prompt/prompt.py
octopus_sensing_sara/interaction_module/prompts/system_prompt/__init__.py
octopus_sensing_sara/interaction_module/prompts/system_prompt/handler.py
octopus_sensing_sara/interaction_module/prompts/system_prompt/prompt.py
octopus_sensing_sara/interaction_module/run.py
octopus_sensing_sara/interaction_module/services/__init__.py
octopus_sensing_sara/interaction_module/services/conversation_service.py
octopus_sensing_sara/interaction_module/services/memory_service.py
octopus_sensing_sara/interaction_module/services/user_service.py
octopus_sensing_sara/interaction_module/storage/__init__.py
octopus_sensing_sara/interaction_module/storage/database.py
octopus_sensing_sara-1.0.dist-info/METADATA
octopus_sensing_sara-1.0.dist-info/WHEEL
octopus_sensing_sara-1.0.dist-info/RECORD
