Metadata-Version: 2.1
Name: octopus-sensing-sara
Version: 1.0
Summary: An empathetic conversational AI companion for Octopus Sensing
License: GPL-3.0-or-later
Author: Nastaran
Requires-Python: >=3.12,<3.13
Classifier: License :: OSI Approved :: GNU General Public License v3 or later (GPLv3+)
Classifier: Programming Language :: Python :: 3
Classifier: Programming Language :: Python :: 3.12
Requires-Dist: dotenv (>=0.9.9,<0.10.0)
Requires-Dist: fastapi (>=0.121.0,<0.122.0)
Requires-Dist: octopus-sensing (>=4.4.4,<5.0.0)
Requires-Dist: octopus-sensing-processing (>=1.0.2,<2.0.0)
Requires-Dist: pydantic (>=2.12.4,<3.0.0)
Requires-Dist: pydantic-settings (>=2.11.0,<3.0.0)
Requires-Dist: tornado (>=6.5.2,<7.0.0)
Requires-Dist: uvicorn (>=0.38.0,<0.39.0)
